{
  "id": "57d58ba7-713d-4bd0-8db8-7f99d2dc1aa7",
  "prevId": "abf1621c-374d-4252-b261-d9f9e5e7a0cd",
  "version": "7",
  "dialect": "postgresql",
  "tables": {
    "public.lessons": {
      "name": "lessons",
      "schema": "",
      "columns": {
        "id": {
          "name": "id",
          "type": "varchar(191)",
          "primaryKey": true,
          "notNull": true
        },
        "title": {
          "name": "title",
          "type": "varchar(255)",
          "primaryKey": false,
          "notNull": true
        },
        "description": {
          "name": "description",
          "type": "text",
          "primaryKey": false,
          "notNull": true
        },
        "type": {
          "name": "type",
          "type": "varchar(32)",
          "primaryKey": false,
          "notNull": true
        },
        "media_url": {
          "name": "media_url",
          "type": "text",
          "primaryKey": false,
          "notNull": false
        },
        "duration_min": {
          "name": "duration_min",
          "type": "integer",
          "primaryKey": false,
          "notNull": true
        },
        "difficulty": {
          "name": "difficulty",
          "type": "varchar(32)",
          "primaryKey": false,
          "notNull": true
        },
        "eco_points": {
          "name": "eco_points",
          "type": "integer",
          "primaryKey": false,
          "notNull": true
        },
        "tags": {
          "name": "tags",
          "type": "jsonb",
          "primaryKey": false,
          "notNull": true,
          "default": "'[]'::jsonb"
        },
        "created_at": {
          "name": "created_at",
          "type": "timestamp with time zone",
          "primaryKey": false,
          "notNull": true,
          "default": "now()"
        },
        "updated_at": {
          "name": "updated_at",
          "type": "timestamp with time zone",
          "primaryKey": false,
          "notNull": true,
          "default": "now()"
        }
      },
      "indexes": {},
      "foreignKeys": {},
      "compositePrimaryKeys": {},
      "uniqueConstraints": {},
      "policies": {},
      "checkConstraints": {},
      "isRLSEnabled": false
    },
    "public.points_log": {
      "name": "points_log",
      "schema": "",
      "columns": {
        "id": {
          "name": "id",
          "type": "varchar(191)",
          "primaryKey": true,
          "notNull": true
        },
        "user_id": {
          "name": "user_id",
          "type": "varchar(191)",
          "primaryKey": false,
          "notNull": true
        },
        "delta": {
          "name": "delta",
          "type": "integer",
          "primaryKey": false,
          "notNull": true
        },
        "reason": {
          "name": "reason",
          "type": "text",
          "primaryKey": false,
          "notNull": false
        },
        "activity_type": {
          "name": "activity_type",
          "type": "varchar(64)",
          "primaryKey": false,
          "notNull": false
        },
        "activity_id": {
          "name": "activity_id",
          "type": "varchar(191)",
          "primaryKey": false,
          "notNull": false
        },
        "created_at": {
          "name": "created_at",
          "type": "timestamp with time zone",
          "primaryKey": false,
          "notNull": true,
          "default": "now()"
        }
      },
      "indexes": {},
      "foreignKeys": {
        "points_log_user_id_users_id_fk": {
          "name": "points_log_user_id_users_id_fk",
          "tableFrom": "points_log",
          "tableTo": "users",
          "columnsFrom": [
            "user_id"
          ],
          "columnsTo": [
            "id"
          ],
          "onDelete": "cascade",
          "onUpdate": "no action"
        }
      },
      "compositePrimaryKeys": {},
      "uniqueConstraints": {},
      "policies": {},
      "checkConstraints": {},
      "isRLSEnabled": false
    },
    "public.quiz_attempts": {
      "name": "quiz_attempts",
      "schema": "",
      "columns": {
        "id": {
          "name": "id",
          "type": "varchar(191)",
          "primaryKey": true,
          "notNull": true
        },
        "user_id": {
          "name": "user_id",
          "type": "varchar(191)",
          "primaryKey": false,
          "notNull": true
        },
        "quiz_id": {
          "name": "quiz_id",
          "type": "varchar(191)",
          "primaryKey": false,
          "notNull": true
        },
        "score": {
          "name": "score",
          "type": "integer",
          "primaryKey": false,
          "notNull": true
        },
        "total_questions": {
          "name": "total_questions",
          "type": "integer",
          "primaryKey": false,
          "notNull": true
        },
        "correct_answers": {
          "name": "correct_answers",
          "type": "integer",
          "primaryKey": false,
          "notNull": true
        },
        "time_spent": {
          "name": "time_spent",
          "type": "integer",
          "primaryKey": false,
          "notNull": true
        },
        "answers": {
          "name": "answers",
          "type": "jsonb",
          "primaryKey": false,
          "notNull": true
        },
        "passed": {
          "name": "passed",
          "type": "boolean",
          "primaryKey": false,
          "notNull": true
        },
        "completed_at": {
          "name": "completed_at",
          "type": "timestamp with time zone",
          "primaryKey": false,
          "notNull": true,
          "default": "now()"
        }
      },
      "indexes": {},
      "foreignKeys": {
        "quiz_attempts_user_id_users_id_fk": {
          "name": "quiz_attempts_user_id_users_id_fk",
          "tableFrom": "quiz_attempts",
          "tableTo": "users",
          "columnsFrom": [
            "user_id"
          ],
          "columnsTo": [
            "id"
          ],
          "onDelete": "cascade",
          "onUpdate": "no action"
        },
        "quiz_attempts_quiz_id_quizzes_id_fk": {
          "name": "quiz_attempts_quiz_id_quizzes_id_fk",
          "tableFrom": "quiz_attempts",
          "tableTo": "quizzes",
          "columnsFrom": [
            "quiz_id"
          ],
          "columnsTo": [
            "id"
          ],
          "onDelete": "cascade",
          "onUpdate": "no action"
        }
      },
      "compositePrimaryKeys": {},
      "uniqueConstraints": {},
      "policies": {},
      "checkConstraints": {},
      "isRLSEnabled": false
    },
    "public.quizzes": {
      "name": "quizzes",
      "schema": "",
      "columns": {
        "id": {
          "name": "id",
          "type": "varchar(191)",
          "primaryKey": true,
          "notNull": true
        },
        "title": {
          "name": "title",
          "type": "varchar(255)",
          "primaryKey": false,
          "notNull": true
        },
        "description": {
          "name": "description",
          "type": "text",
          "primaryKey": false,
          "notNull": false
        },
        "lesson_id": {
          "name": "lesson_id",
          "type": "varchar(191)",
          "primaryKey": false,
          "notNull": false
        },
        "questions": {
          "name": "questions",
          "type": "jsonb",
          "primaryKey": false,
          "notNull": true
        },
        "time_limit": {
          "name": "time_limit",
          "type": "integer",
          "primaryKey": false,
          "notNull": false
        },
        "passing_score": {
          "name": "passing_score",
          "type": "integer",
          "primaryKey": false,
          "notNull": true,
          "default": 70
        },
        "eco_points": {
          "name": "eco_points",
          "type": "integer",
          "primaryKey": false,
          "notNull": true,
          "default": 10
        },
        "difficulty": {
          "name": "difficulty",
          "type": "varchar(32)",
          "primaryKey": false,
          "notNull": true,
          "default": "'medium'"
        },
        "created_at": {
          "name": "created_at",
          "type": "timestamp with time zone",
          "primaryKey": false,
          "notNull": true,
          "default": "now()"
        },
        "updated_at": {
          "name": "updated_at",
          "type": "timestamp with time zone",
          "primaryKey": false,
          "notNull": true,
          "default": "now()"
        }
      },
      "indexes": {},
      "foreignKeys": {
        "quizzes_lesson_id_lessons_id_fk": {
          "name": "quizzes_lesson_id_lessons_id_fk",
          "tableFrom": "quizzes",
          "tableTo": "lessons",
          "columnsFrom": [
            "lesson_id"
          ],
          "columnsTo": [
            "id"
          ],
          "onDelete": "cascade",
          "onUpdate": "no action"
        }
      },
      "compositePrimaryKeys": {},
      "uniqueConstraints": {},
      "policies": {},
      "checkConstraints": {},
      "isRLSEnabled": false
    },
    "public.user_completed_lessons": {
      "name": "user_completed_lessons",
      "schema": "",
      "columns": {
        "user_id": {
          "name": "user_id",
          "type": "varchar(191)",
          "primaryKey": false,
          "notNull": true
        },
        "lesson_id": {
          "name": "lesson_id",
          "type": "varchar(191)",
          "primaryKey": false,
          "notNull": true
        },
        "completed_at": {
          "name": "completed_at",
          "type": "timestamp with time zone",
          "primaryKey": false,
          "notNull": true,
          "default": "now()"
        }
      },
      "indexes": {},
      "foreignKeys": {
        "user_completed_lessons_user_id_users_id_fk": {
          "name": "user_completed_lessons_user_id_users_id_fk",
          "tableFrom": "user_completed_lessons",
          "tableTo": "users",
          "columnsFrom": [
            "user_id"
          ],
          "columnsTo": [
            "id"
          ],
          "onDelete": "cascade",
          "onUpdate": "no action"
        },
        "user_completed_lessons_lesson_id_lessons_id_fk": {
          "name": "user_completed_lessons_lesson_id_lessons_id_fk",
          "tableFrom": "user_completed_lessons",
          "tableTo": "lessons",
          "columnsFrom": [
            "lesson_id"
          ],
          "columnsTo": [
            "id"
          ],
          "onDelete": "cascade",
          "onUpdate": "no action"
        }
      },
      "compositePrimaryKeys": {
        "user_completed_lessons_user_id_lesson_id_pk": {
          "name": "user_completed_lessons_user_id_lesson_id_pk",
          "columns": [
            "user_id",
            "lesson_id"
          ]
        }
      },
      "uniqueConstraints": {},
      "policies": {},
      "checkConstraints": {},
      "isRLSEnabled": false
    },
    "public.user_progress": {
      "name": "user_progress",
      "schema": "",
      "columns": {
        "user_id": {
          "name": "user_id",
          "type": "varchar(191)",
          "primaryKey": true,
          "notNull": true
        },
        "total_points": {
          "name": "total_points",
          "type": "integer",
          "primaryKey": false,
          "notNull": true,
          "default": 0
        },
        "level": {
          "name": "level",
          "type": "integer",
          "primaryKey": false,
          "notNull": true,
          "default": 1
        },
        "badges": {
          "name": "badges",
          "type": "jsonb",
          "primaryKey": false,
          "notNull": true,
          "default": "'[]'::jsonb"
        },
        "completed_lessons_count": {
          "name": "completed_lessons_count",
          "type": "integer",
          "primaryKey": false,
          "notNull": true,
          "default": 0
        },
        "streak": {
          "name": "streak",
          "type": "integer",
          "primaryKey": false,
          "notNull": true,
          "default": 0
        },
        "updated_at": {
          "name": "updated_at",
          "type": "timestamp with time zone",
          "primaryKey": false,
          "notNull": true,
          "default": "now()"
        }
      },
      "indexes": {},
      "foreignKeys": {
        "user_progress_user_id_users_id_fk": {
          "name": "user_progress_user_id_users_id_fk",
          "tableFrom": "user_progress",
          "tableTo": "users",
          "columnsFrom": [
            "user_id"
          ],
          "columnsTo": [
            "id"
          ],
          "onDelete": "cascade",
          "onUpdate": "no action"
        }
      },
      "compositePrimaryKeys": {},
      "uniqueConstraints": {},
      "policies": {},
      "checkConstraints": {},
      "isRLSEnabled": false
    },
    "public.users": {
      "name": "users",
      "schema": "",
      "columns": {
        "id": {
          "name": "id",
          "type": "varchar(191)",
          "primaryKey": true,
          "notNull": true
        },
        "email": {
          "name": "email",
          "type": "varchar(255)",
          "primaryKey": false,
          "notNull": true
        },
        "first_name": {
          "name": "first_name",
          "type": "varchar(120)",
          "primaryKey": false,
          "notNull": false
        },
        "last_name": {
          "name": "last_name",
          "type": "varchar(120)",
          "primaryKey": false,
          "notNull": false
        },
        "role": {
          "name": "role",
          "type": "varchar(32)",
          "primaryKey": false,
          "notNull": true,
          "default": "'student'"
        },
        "created_at": {
          "name": "created_at",
          "type": "timestamp with time zone",
          "primaryKey": false,
          "notNull": true,
          "default": "now()"
        },
        "updated_at": {
          "name": "updated_at",
          "type": "timestamp with time zone",
          "primaryKey": false,
          "notNull": true,
          "default": "now()"
        }
      },
      "indexes": {},
      "foreignKeys": {},
      "compositePrimaryKeys": {},
      "uniqueConstraints": {},
      "policies": {},
      "checkConstraints": {},
      "isRLSEnabled": false
    }
  },
  "enums": {},
  "schemas": {},
  "sequences": {},
  "roles": {},
  "policies": {},
  "views": {},
  "_meta": {
    "columns": {},
    "schemas": {},
    "tables": {}
  }
}